CHANGES.txt
MANIFEST.in
README.rst
setup.py
missingbits/__init__.py
missingbits/options.py
missingbits/recipe.py
missingbits/stack.py
missingbits.egg-info/PKG-INFO
missingbits.egg-info/SOURCES.txt
missingbits.egg-info/dependency_links.txt
missingbits.egg-info/entry_points.txt
missingbits.egg-info/not-zip-safe
missingbits.egg-info/requires.txt
missingbits.egg-info/top_level.txt