Metadata-Version: 1.0
Name: missingbits
Version: 0.0.14
Summary: Buildout parts that make you smile
Home-page: http://github.com/isotoma/missingbits
Author: John Carr
Author-email: john.carr@isotoma.com
License: Apache Software License
Keywords: buildout
Platform: UNKNOWN
Classifier: Framework :: Buildout
Classifier: Framework :: Buildout :: Recipe
Classifier: Intended Audience :: System Administrators
Classifier: Operating System :: POSIX
Classifier: License :: OSI Approved :: Zope Public License
